{
  "kind": "collectionType",
  "collectionName": "products",
  "info": {
    "name": "Product",
    "description": ""
  },
  "options": {
    "increments": true,
    "timestamps": true,
    "draftAndPublish": false
  },
  "pluginOptions": {},
  "attributes": {
    "title": {
      "type": "string",
      "required": true
    },
    "price": {
      "type": "decimal",
      "required": true
    },
    "oldPrice": {
      "type": "decimal"
    },
    "description": {
      "type": "richtext",
      "required": true
    },
    "cover": {
      "model": "file",
      "via": "related",
      "allowedTypes": [
        "images"
      ],
      "plugin": "upload",
      "required": false,
      "pluginOptions": {}
    },
    "gallery": {
      "collection": "file",
      "via": "related",
      "allowedTypes": [
        "images"
      ],
      "plugin": "upload",
      "required": false,
      "pluginOptions": {}
    },
    "categories": {
      "via": "products",
      "collection": "category"
    }
  }
}
